{
    "name": "example",
    "icon": "chart-pie",
    "displayName": "Charts",
    "cards": [
        {
            "key": "value_1750203093478",
            "width": 4,
            "height": 8,
            "icon": "circle-gauge",
            "name": "Radial Bar Chart",
            "description": "Displays a radial bar chart using Recharts",
            "type": "value",
            "params": {
                "nameKey": "name",
                "dataKey": "score",
                "displayLegend": "false",
                "startAngle": "90",
                "endAngle": "-270",
                "aspect": "1.7"
            }
        },
        {
            "key": "value_1750205567388",
            "width": 4,
            "height": 8,
            "icon": "chart-pie",
            "name": "Pie Chart",
            "description": "Displays a pie chart using Recharts",
            "type": "value",
            "params": {
                "nameKey": "name",
                "dataKey": "score"
            }
        },
        {
            "key": "value_1750207235370",
            "width": 4,
            "height": 8,
            "icon": "chart-column",
            "name": "Bar Chart",
            "description": "Displays a bar chart using Recharts",
            "type": "value",
            "params": {
                "nameKey": "name",
                "dataKey": "score"
            }
        },
        {
            "key": "value_1750208012341",
            "width": 4,
            "height": 8,
            "icon": "chart-network",
            "name": "Radar Chart",
            "description": "Displays a radar chart using Recharts",
            "type": "value",
            "params": {
                "nameKey": "name",
                "dataKey": "score"
            }
        },
        {
            "key": "value_1750208806989",
            "width": 4,
            "height": 8,
            "icon": "chart-area",
            "name": "Area Chart",
            "description": "Displays an area chart using Recharts",
            "type": "value",
            "params": {
                "nameKey": "name",
                "dataKey": "score"
            }
        },
        {
            "key": "value_1750209418277",
            "width": 4,
            "height": 8,
            "icon": "chart-line",
            "name": "Line Chart",
            "description": "Displays a line chart using Recharts",
            "type": "value",
            "params": {
                "nameKey": "name",
                "dataKey": "score"
            }
        },
        {
            "key": "action_1751733782443",
            "width": 2,
            "height": 6,
            "icon": "search",
            "displayResponse": true,
            "name": "list players",
            "type": "action",
            "description": "Returns a list of players objects. You can filter the results by passing itemsPerPage, page, search, orderBy and orderDirection parameters.",
            "params": {
                "itemsPerPage": "number of items per page (optional)",
                "page": "page number to retrieve (optional)",
                "search": "search term to filter the results (optional)",
                "orderBy": "field to order the results by (optional)",
                "orderDirection": "direction to order the results by (asc or desc) (optional)"
            }
        },
        {
            "key": "value_1753540637550",
            "width": 1,
            "height": 4,
            "icon": "tag",
            "type": "value",
            "name": "blank",
            "displayFrame": true,
            "displayIcon": false,
            "displayTitle": false
        }
    ],
    "layouts": {
        "lg": [
            {
                "w": 17,
                "h": 13,
                "x": 0,
                "y": 0,
                "i": "value_1750203093478",
                "moved": false,
                "static": false,
                "isResizable": true
            },
            {
                "w": 27,
                "h": 11,
                "x": 0,
                "y": 13,
                "i": "value_1750205567388",
                "moved": false,
                "static": false,
                "isResizable": true
            },
            {
                "w": 37,
                "h": 11,
                "x": 50,
                "y": 0,
                "i": "value_1750207235370",
                "moved": false,
                "static": false,
                "isResizable": true
            },
            {
                "w": 28,
                "h": 13,
                "x": 59,
                "y": 11,
                "i": "value_1750208012341",
                "moved": false,
                "static": false,
                "isResizable": true
            },
            {
                "w": 32,
                "h": 5,
                "x": 27,
                "y": 19,
                "i": "value_1750208806989",
                "moved": false,
                "static": false,
                "isResizable": true
            },
            {
                "w": 32,
                "h": 6,
                "x": 27,
                "y": 13,
                "i": "value_1750209418277",
                "moved": false,
                "static": false,
                "isResizable": true
            },
            {
                "w": 33,
                "h": 13,
                "x": 17,
                "y": 0,
                "i": "action_1751733782443",
                "moved": false,
                "static": false,
                "isResizable": true
            },
            {
                "w": 9,
                "h": 2,
                "x": 50,
                "y": 11,
                "i": "value_1753540637550",
                "moved": false,
                "static": false,
                "isResizable": true
            }
        ],
        "md": [
            {
                "w": 25,
                "h": 13,
                "x": 38,
                "y": 0,
                "i": "value_1750203093478",
                "moved": false,
                "static": false,
                "isResizable": true
            },
            {
                "w": 25,
                "h": 11,
                "x": 38,
                "y": 13,
                "i": "value_1750205567388",
                "moved": false,
                "static": false,
                "isResizable": true
            },
            {
                "w": 19,
                "h": 9,
                "x": 0,
                "y": 13,
                "i": "value_1750207235370",
                "moved": false,
                "static": false,
                "isResizable": true
            },
            {
                "w": 19,
                "h": 9,
                "x": 19,
                "y": 13,
                "i": "value_1750208012341",
                "moved": false,
                "static": false,
                "isResizable": true
            },
            {
                "w": 38,
                "h": 5,
                "x": 0,
                "y": 22,
                "i": "value_1750208806989",
                "moved": false,
                "static": false,
                "isResizable": true
            },
            {
                "w": 25,
                "h": 5,
                "x": 38,
                "y": 24,
                "i": "value_1750209418277",
                "moved": false,
                "static": false,
                "isResizable": true
            },
            {
                "w": 38,
                "h": 13,
                "x": 0,
                "y": 0,
                "i": "action_1751733782443",
                "moved": false,
                "static": false,
                "isResizable": true
            },
            {
                "w": 38,
                "h": 2,
                "x": 0,
                "y": 27,
                "i": "value_1753540637550",
                "moved": false,
                "static": false,
                "isResizable": true
            }
        ],
        "sm": [
            {
                "w": 2,
                "h": 15,
                "x": 0,
                "y": 15,
                "i": "value_1750203093478",
                "moved": false,
                "static": false
            },
            {
                "w": 2,
                "h": 15,
                "x": 0,
                "y": 30,
                "i": "value_1750205567388",
                "moved": false,
                "static": false
            },
            {
                "w": 2,
                "h": 18,
                "x": 0,
                "y": 45,
                "i": "value_1750207235370",
                "moved": false,
                "static": false
            },
            {
                "w": 2,
                "h": 19,
                "x": 0,
                "y": 63,
                "i": "value_1750208012341",
                "moved": false,
                "static": false
            },
            {
                "w": 2,
                "h": 7,
                "x": 0,
                "y": 82,
                "i": "value_1750208806989",
                "moved": false,
                "static": false
            },
            {
                "w": 2,
                "h": 10,
                "x": 0,
                "y": 89,
                "i": "value_1750209418277",
                "moved": false,
                "static": false
            },
            {
                "w": 2,
                "h": 15,
                "x": 0,
                "y": 0,
                "i": "action_1751733782443",
                "moved": false,
                "static": false
            },
            {
                "i": "value_1753540637550",
                "x": 0,
                "y": 0,
                "w": 1,
                "h": 5,
                "isResizable": true
            }
        ],
        "xs": [
            {
                "w": 2,
                "h": 15,
                "x": 0,
                "y": 15,
                "i": "value_1750203093478",
                "moved": false,
                "static": false
            },
            {
                "w": 2,
                "h": 15,
                "x": 0,
                "y": 30,
                "i": "value_1750205567388",
                "moved": false,
                "static": false
            },
            {
                "w": 2,
                "h": 18,
                "x": 0,
                "y": 45,
                "i": "value_1750207235370",
                "moved": false,
                "static": false
            },
            {
                "w": 2,
                "h": 19,
                "x": 0,
                "y": 63,
                "i": "value_1750208012341",
                "moved": false,
                "static": false
            },
            {
                "w": 2,
                "h": 7,
                "x": 0,
                "y": 82,
                "i": "value_1750208806989",
                "moved": false,
                "static": false
            },
            {
                "w": 2,
                "h": 10,
                "x": 0,
                "y": 89,
                "i": "value_1750209418277",
                "moved": false,
                "static": false
            },
            {
                "w": 2,
                "h": 15,
                "x": 0,
                "y": 0,
                "i": "action_1751733782443",
                "moved": false,
                "static": false
            },
            {
                "i": "value_1753540637550",
                "x": 0,
                "y": 0,
                "w": 1,
                "h": 5,
                "isResizable": true
            }
        ]
    },
    "autopilot": false,
    "rules": [
        "ejecuta la accion list"
    ],
    "rulesCode": "execute_action(\"/api/core/v1/boards/test/actions/list\", {});"
}